pandascharm.py
pandas_charm-0.3.0.dist-info/LICENSE.txt
pandas_charm-0.3.0.dist-info/METADATA
pandas_charm-0.3.0.dist-info/WHEEL
pandas_charm-0.3.0.dist-info/top_level.txt
pandas_charm-0.3.0.dist-info/RECORD
