Metadata-Version: 2.1
Name: pandas-charm
Version: 0.3.0
Summary: A small Python library for getting character matrices (alignments) into and out of pandas
Home-page: https://github.com/jmenglund/pandas-charm
Author: Markus Englund
Author-email: jan.markus.englund@gmail.com
License: MIT
Keywords: alignment,BioPython,DendroPy,pandas
Platform: UNKNOWN
Classifier: Development Status :: 5 - Production/Stable
Classifier: Intended Audience :: Science/Research
Classifier: License :: OSI Approved :: MIT License
Classifier: Operating System :: OS Independent
Classifier: Programming Language :: Python
Classifier: Programming Language :: Python :: 2
Classifier: Programming Language :: Python :: 2.7
Classifier: Programming Language :: Python :: 3
Classifier: Programming Language :: Python :: 3.5
Classifier: Programming Language :: Python :: 3.6
Requires-Dist: pandas (>=0.21)
Provides-Extra: testing
Requires-Dist: coverage ; extra == 'testing'
Requires-Dist: pytest ; extra == 'testing'
Requires-Dist: biopython ; extra == 'testing'
Requires-Dist: dendropy ; extra == 'testing'
